{
 "cells": [
  {
   "cell_type": "code",
   "execution_count": null,
   "metadata": {},
   "outputs": [],
   "source": [
    "import torch\n",
    "from torch import nn\n",
    "from torch.utils.data import Dataset, DataLoader\n",
    "\n",
    "import torchvision\n",
    "from torchvision.datasets import ImageFolder\n",
    "from torchvision import transforms\n",
    "\n",
    "import random\n",
    "\n",
    "from PIL import Image\n",
    "\n",
    "from pathlib import Path\n",
    "import os\n",
    "\n",
    "import collections\n",
    "\n",
    "from sklearn.model_selection import train_test_split\n",
    "\n",
    "dtype = torch.float\n",
    "device = torch.device(\"cuda\" if torch.cuda.is_available() else \"cpu\")"
   ]
  },
  {
   "cell_type": "code",
   "execution_count": null,
   "metadata": {},
   "outputs": [],
   "source": [
    "nepochs = 100\n",
    "# nbatchs = 30\n",
    "nbatchs_per_ep = 30\n",
    "nbatchs_per_ev = 512\n",
    "# embed_size = 50\n",
    "lr = 2e-3\n",
    "\n",
    "\n",
    "xx = os.path.join(\"../checkpoints\")\n",
    "if not os.path.exists(xx):\n",
    "    os.makedirs(xx)"
   ]
  },
  {
   "cell_type": "code",
   "execution_count": null,
   "metadata": {},
   "outputs": [],
   "source": [
    "class LogoDataset(Dataset):\n",
    "    def __init__(\n",
    "        self,\n",
    "        folder_dataset: Path,\n",
    "        transform=None,\n",
    "    ) -> None:\n",
    "        self.dataset = ImageFolder(root=folder_dataset)\n",
    "        self.transform = transform\n",
    "\n",
    "    def __len__(self) -> int:\n",
    "        return len(self.dataset.imgs)\n",
    "\n",
    "    def __getitem__(\n",
    "        self,\n",
    "        index: int,\n",
    "    ) -> tuple[torch.Tensor, torch.Tensor, torch.Tensor]:\n",
    "\n",
    "        x1 = random.choice(self.dataset.imgs)\n",
    "\n",
    "        is_same = random.randint(0, 1)\n",
    "        if is_same:\n",
    "            while True:\n",
    "                x2 = random.choice(self.dataset.imgs)\n",
    "                if x1[1] == x2[1]:\n",
    "                    break\n",
    "        else:\n",
    "            while True:\n",
    "                x2 = random.choice(self.dataset.imgs)\n",
    "                if x1[1] != x2[1]:\n",
    "                    break\n",
    "\n",
    "        im1 = Image.open(x1[0]).convert(\"RGBA\").convert(\"L\")\n",
    "        im2 = Image.open(x2[0]).convert(\"RGBA\").convert(\"L\")\n",
    "\n",
    "        if self.transform is not None:\n",
    "            im1 = self.transform(im1)\n",
    "            im2 = self.transform(im2)\n",
    "\n",
    "        return im1, im2, torch.tensor([int(x1[1] == x2[1])], dtype=dtype)\n",
    "\n",
    "\n",
    "transform = transforms.Compose(\n",
    "    [\n",
    "        transforms.Resize((264, 400)),\n",
    "        transforms.ToTensor(),\n",
    "    ]\n",
    ")\n",
    "\n",
    "\n",
    "dataset = LogoDataset(\n",
    "    folder_dataset=Path(\"../logo2k_dataset\"),\n",
    "    transform=transform,\n",
    ")\n",
    "\n",
    "train_loader = DataLoader(\n",
    "    dataset=dataset,\n",
    "    shuffle=False,\n",
    "    num_workers=0,\n",
    "    batch_size=nbatchs_per_ep,\n",
    ")"
   ]
  },
  {
   "cell_type": "code",
   "execution_count": null,
   "metadata": {},
   "outputs": [],
   "source": [
    "class SiameseNet(nn.Module):\n",
    "    def __init__(self) -> None:\n",
    "        super(SiameseNet, self).__init__()\n",
    "\n",
    "        # self.encoder = torchvision.models.vgg11(progress=False) # vgg11 takes so much memory!\n",
    "\n",
    "        self.encoder = torchvision.models.alexnet(progress=False)\n",
    "        self.encoder.features[0] = nn.Conv2d(\n",
    "            1, 64, kernel_size=(11, 11), stride=(4, 4), padding=(2, 2)\n",
    "        )\n",
    "\n",
    "    def forward(self, x1: torch.tensor, x2: torch.tensor) -> torch.tensor:\n",
    "        nbatchs = x1.size(0)\n",
    "        x1 = self.encoder(x1).view((nbatchs, -1))\n",
    "        x2 = self.encoder(x2).view((nbatchs, -1))\n",
    "        \n",
    "        return x1, x2"
   ]
  },
  {
   "cell_type": "code",
   "execution_count": null,
   "metadata": {},
   "outputs": [],
   "source": [
    "class ContrastiveLoss(nn.Module):\n",
    "    def __init__(\n",
    "        self,\n",
    "        margin:int,\n",
    "        reduce:bool,\n",
    "    ) -> None:\n",
    "        super(ContrastiveLoss, self).__init__()\n",
    "\n",
    "        if isinstance(margin, torch.Tensor):\n",
    "            self.margin = margin\n",
    "        else:\n",
    "            self.margin = torch.tensor([margin], dtype=dtype).to(device)\n",
    "\n",
    "        self.reduce = reduce\n",
    "        \n",
    "    def forward(\n",
    "        self, x1: torch.Tensor, x2: torch.Tensor, y: torch.Tensor\n",
    "    ) -> torch.Tensor:\n",
    "        dist2 = torch.nn.functional.pairwise_distance(x1, x2, keepdim=True).pow(2)\n",
    "        out = (1 - y) * dist2 + y * torch.clamp(self.margin - dist2, min=0.0)\n",
    "        \n",
    "        if self.reduce:\n",
    "            out = 0.5 * out.mean()\n",
    "        return out"
   ]
  },
  {
   "cell_type": "code",
   "execution_count": null,
   "metadata": {},
   "outputs": [],
   "source": [
    "model = SiameseNet()\n",
    "model = nn.DataParallel(model)\n",
    "model = model.to(device)\n",
    "\n",
    "loss_fn = ContrastiveLoss(margin=1.25, reduce=True)\n",
    "optim = torch.optim.Adam(model.parameters(), lr=lr)"
   ]
  },
  {
   "cell_type": "code",
   "execution_count": null,
   "metadata": {},
   "outputs": [],
   "source": [
    "loss_history = []\n",
    "threshold  =.5\n",
    "\n",
    "for epoch in range(nepochs):\n",
    "    model.train()\n",
    "    accuracy = 0\n",
    "    for batch, (x1, x2, y) in enumerate(train_loader):\n",
    "        x1, x2, y = x1.to(device), x2.to(device), y.to(device)\n",
    "\n",
    "        optim.zero_grad()\n",
    "\n",
    "        # features\n",
    "        out1, out2 = model(x1, x2)\n",
    "\n",
    "        loss = loss_fn(out1, out2, y)\n",
    "        loss.backward()\n",
    "        optim.step()\n",
    "\n",
    "        if not batch % 100:\n",
    "            print(\n",
    "                f\"epoch {epoch+1}/{nepochs} batch {batch+1}/{len(train_loader)} loss {loss.item():.4f}\"\n",
    "            )\n",
    "            \n",
    "        #     with torch.no_grad():\n",
    "        #         distance = torch.nn.functional.pairwise_distance(out1, out2, keepdim=True)\n",
    "        #         yhat = distance < threshold\n",
    "        #         accuracy = (y == yhat).sum() \n",
    "   \n",
    "\n",
    "    loss_history.append(loss.item())\n",
    "    if not epoch % 1:\n",
    "        torch.save(\n",
    "            {\n",
    "                \"epoch\": epoch,\n",
    "                \"loss\": loss.item(),\n",
    "                \"plot_performance\": loss_history,\n",
    "                \"model\": model.state_dict(),\n",
    "                \"optimizer\": optim.state_dict(),\n",
    "            },\n",
    "            f\"../checkpoints/checkpoint_{epoch}.pkl\",\n",
    "        )"
   ]
  },
  {
   "cell_type": "code",
   "execution_count": null,
   "metadata": {},
   "outputs": [],
   "source": [
    "def evaluate_siamese_network(dataset_loader, model, threshold):\n",
    "    if model is None:\n",
    "        model = torch.load(\n",
    "            \"../checkpoints_logo_dataset/checkpoint_24.pkl\", map_location=device\n",
    "        )\n",
    "\n",
    "    model.eval()\n",
    "    accuracy = 0\n",
    "    true_positive = false_positive = true_negative = false_negative = 0\n",
    "    Outcome = collections.namedtuple(\n",
    "        \"Outcome\",\n",
    "        [\n",
    "            \"accuracy\",\n",
    "            \"true_positive\",\n",
    "            \"true_negative\",\n",
    "            \"false_positive\",\n",
    "            \"false_negative\",\n",
    "        ],\n",
    "    )\n",
    "\n",
    "    dataset_loader = DataLoader(\n",
    "        dataset=dataset,\n",
    "        shuffle=False,\n",
    "        num_workers=0,\n",
    "        batch_size=nbatchs_per_ev,\n",
    "    )\n",
    "\n",
    "    loss_fn = ContrastiveLoss(margin=1, reduce=False)\n",
    "    for x1, x2, y in dataset_loader:\n",
    "        x1, x2, y = x1.to(device), x2.to(device), y.to(device)\n",
    "\n",
    "        out1, out2 = model(x1, x2)\n",
    "        dist = torch.nn.functional.pairwise_distance(out1, out2, keepdim=True)\n",
    "\n",
    "        yhat = (dist < threshold)\n",
    "        correct = yhat == y\n",
    "\n",
    "        for c, yh in zip(correct, yhat):\n",
    "            if yh:\n",
    "                if c:\n",
    "                    true_positive += 1\n",
    "                else:\n",
    "                    false_positive += 1\n",
    "            else:\n",
    "                if c:\n",
    "                    true_negative += 1\n",
    "                else:\n",
    "                    false_negative += 1\n",
    "            accuracy += int(c)\n",
    "\n",
    "    return Outcome(\n",
    "        accuracy=accuracy/y.size(0),\n",
    "        true_positive=true_positive,\n",
    "        false_positive=false_positive,\n",
    "        true_negative=true_negative,\n",
    "        false_negative=false_negative\n",
    "    )\n"
   ]
  },
  {
   "cell_type": "code",
   "execution_count": null,
   "metadata": {},
   "outputs": [],
   "source": [
    "outcome = evaluate_siamese_network(train_loader, model, .5)\n",
    "print(f\"Accuracy: {outcome.accuracy:0.2f}\")\n",
    "true_positive = outcome.true_positive\n",
    "false_negative = outcome.false_negative\n",
    "true_negative = outcome.true_negative\n",
    "false_positive = outcome.false_positive\n",
    "\n",
    "print(f\"True Positive Rate: {true_positive/(true_positive + false_negative): 0.2f}\")\n",
    "print(f\"True Negative Rate: {true_negative/(true_negative + false_positive):0.2f}\")\n",
    "print(f\"Precision: {outcome.true_positive/(true_positive + false_positive):0.2f}\")\n",
    "print(f\"False Negative Rate: {false_negative/(false_negative + true_positive):0.2f}\")\n",
    "print(f\"False Positive Rate: {false_positive/(false_positive + true_negative): 0.2f}\")"
   ]
  },
  {
   "cell_type": "code",
   "execution_count": null,
   "metadata": {},
   "outputs": [],
   "source": [
    "import matplotlib.pyplot as plt\n",
    "\n",
    "plt.plot(list(range(1, len(loss_history) + 1)), loss_history, label=\"Training loss\")\n",
    "plt.xlabel(\"Iterations\")\n",
    "plt.ylabel(\"Contrastive loss\")\n",
    "plt.legend()\n",
    "plt.grid(True)\n",
    "plt.show()"
   ]
  },
  {
   "cell_type": "code",
   "execution_count": null,
   "metadata": {},
   "outputs": [],
   "source": [
    "nsamples = 20\n",
    "thresh = .5\n",
    "checkpoint = torch.load(\n",
    "    \"../checkpoints/checkpoint_20.pkl\", map_location=device\n",
    ")\n",
    "\n",
    "model = SiameseNet().to(device)\n",
    "model.load_state_dict(checkpoint[\"model\"], strict=False)\n",
    "\n",
    "# model.eval()\n",
    "train_loader = DataLoader(\n",
    "    dataset=dataset,\n",
    "    shuffle=False,\n",
    "    num_workers=0,\n",
    "    batch_size=nsamples,\n",
    ")\n",
    "\n",
    "data = iter(train_loader)\n",
    "x1, x2, y = next(data)\n",
    "x1, x2, y = x1.to(device), x2.to(device), y.to(device)\n",
    "\n",
    "\n",
    "# prediction\n",
    "out1, out2 = model(x1, x2)\n",
    "dist = torch.nn.functional.pairwise_distance(out1, out2, keepdim=True)\n",
    "\n",
    "yhat = dist<thresh\n",
    "# is_same = yhat == y\n",
    "\n",
    "fig, axs = plt.subplots(2, nsamples, figsize=(40,25))\n",
    "for i in range(2):    \n",
    "    for j in range(nsamples):\n",
    "        axs[i,j].set_xticklabels([])\n",
    "        axs[i,j].set_yticklabels([])\n",
    "        axs[i,j].set_aspect('equal')\n",
    "        xx = x1[j].cpu().numpy().transpose(1,2,0)\n",
    "        yg = y[j].int().item()\n",
    "        yp = yhat[j].int().item()\n",
    "\n",
    "        if i:\n",
    "            axs[i,j].imshow(xx, cmap=\"gray\")\n",
    "        if not i:\n",
    "            axs[i,j].set_title(f\"G{yg} P{yp} - {'correct' if yp==yg else 'false'}\")\n",
    "            xx = x2[j].cpu().numpy().transpose(1,2,0)\n",
    "            axs[i,j].imshow(xx, cmap=\"gray\")\n",
    "plt.subplots_adjust(wspace=.05, hspace=-.7)"
   ]
  },
  {
   "cell_type": "code",
   "execution_count": null,
   "metadata": {},
   "outputs": [],
   "source": []
  }
 ],
 "metadata": {
  "kernelspec": {
   "display_name": "Python 3.9.12 ('base')",
   "language": "python",
   "name": "python3"
  },
  "language_info": {
   "codemirror_mode": {
    "name": "ipython",
    "version": 3
   },
   "file_extension": ".py",
   "mimetype": "text/x-python",
   "name": "python",
   "nbconvert_exporter": "python",
   "pygments_lexer": "ipython3",
   "version": "3.9.12"
  },
  "orig_nbformat": 4,
  "vscode": {
   "interpreter": {
    "hash": "9f0194299e911b6a22f0cd3d1c9a66c991d39f48b249be23f24104e40900e329"
   }
  }
 },
 "nbformat": 4,
 "nbformat_minor": 2
}
